watertap_solvers/__init__.py
watertap_solvers/_base.py
watertap_solvers/conftest.py
watertap_solvers/model_debug_mode.py
watertap_solvers/tests/model_debug_example_script.py
watertap_solvers/tests/test_model_debug_mode.py
watertap_solvers/tests/test_solver_wrappers.py
watertap_solvers-24.12.9.dist-info/LICENSE.md
watertap_solvers-24.12.9.dist-info/METADATA
watertap_solvers-24.12.9.dist-info/WHEEL
watertap_solvers-24.12.9.dist-info/top_level.txt
watertap_solvers-24.12.9.dist-info/RECORD
