Metadata-Version: 2.1
Name: watertap-solvers
Version: 24.12.9
License-File: LICENSE.md
Requires-Dist: pyomo
Requires-Dist: idaes-pse
Provides-Extra: testing
Requires-Dist: pytest; extra == "testing"
Requires-Dist: ipython; extra == "testing"
